{
  "success": true,
  "payload": {
    "value": {
      "id": "553ec50e2933",
      "versionId": "7399d2171b5b",
      "creatorId": "2c4e5126ccb9",
      "homeCollectionId": "4b3a1ed4f11c",
      "title": "A Practical Guide To Become a Senior Frontend Developer",
      "detectedLanguage": "en",
      "latestVersion": "7399d2171b5b",
      "latestPublishedVersion": "7399d2171b5b",
      "hasUnpublishedEdits": false,
      "latestRev": 2007,
      "createdAt": 1581408006223,
      "updatedAt": 1586162627908,
      "acceptedAt": 0,
      "firstPublishedAt": 1586103344957,
      "latestPublishedAt": 1586162627700,
      "vote": false,
      "experimentalCss": "",
      "displayAuthor": "",
      "content": {
        "subtitle": "Quarantine Might Be Your Golden Chance",
        "bodyModel": {
          "paragraphs": [
            {
              "name": "1430",
              "type": 3,
              "text": "A Practical Guide To Become a Senior Frontend Developer",
              "markups": []
            },
            {
              "name": "06a5",
              "type": 13,
              "text": "Quarantine Might Be Your Golden Chance",
              "markups": []
            },
            {
              "name": "62a6",
              "type": 1,
              "text": "There are several different definitions for the title ├ö├ç├┐Senior├ö├ç├û and it changes from one company to another. Yet, it├ö├ç├ûs agreed upon that there are are a lot of both hard and soft skills required.",
              "markups": []
            },
            {
              "name": "45ce",
              "type": 1,
              "text": "Chris Coyier wrote an article about character traits and behaviors that a senior frontend developer should have that gives a nice overall picture.",
              "markups": [
                {
                  "type": 3,
                  "start": 0,
                  "end": 30,
                  "href": "https://css-tricks.com/want-senior-developer/",
                  "title": "",
                  "rel": "",
                  "anchorType": 0
                }
              ]
            },
            {
              "name": "4f91",
              "type": 1,
              "text": "In this article, we will cover 12 things you can do to make the best out of these times so that when they are over, you can become a senior frontend developer.",
              "markups": []
            },
            {
              "name": "9363",
              "type": 4,
              "text": "Photo by Ruffa Jane Reyes on Unsplash",
              "markups": [
                {
                  "type": 3,
                  "start": 9,
                  "end": 25,
                  "href": "https://unsplash.com/@opak?utm_source=medium&utm_medium=referral",
                  "title": "",
                  "rel": "photo-creator",
                  "anchorType": 0
                },
                {
                  "type": 3,
                  "start": 29,
                  "end": 37,
                  "href": "https://unsplash.com?utm_source=medium&utm_medium=referral",
                  "title": "",
                  "rel": "photo-source",
                  "anchorType": 0
                }
              ],
              "layout": 1,
              "metadata": {
                "id": "0*G4aXwIEIiN6KfbSm",
                "originalWidth": 4584,
                "originalHeight": 3456,
                "isFeatured": true,
                "unsplashPhotoId": "P6mdg0z5tHc"
              }
            },
            {
              "name": "9302",
              "type": 3,
              "text": "1. Master The Fundamentals",
              "markups": []
            },
            {
              "name": "78e6",
              "type": 1,
              "text": "Senior frontend developers should be very comfortable articulating HTML, JS, and CSS. Additionally, they should have basic concepts about how the internet works including browsers, networks, and servers.",
              "markups": []
            },
            {
              "name": "d7e0",
              "type": 1,
              "text": "This means that concepts like prototypes, event bubbling, call stack, promises, ES6 are no foreign to you. The same applies to CSS, animations, grid systems, naming conventions, and specificity.",
              "markups": []
            },
            {
              "name": "4a7c",
              "type": 1,
              "text": "There are numerous concepts to learn, below you can find some resources that you can skim and look for things you don├ö├ç├ût know about, yet. CSS Reference, Html Reference, Javascript Fundamentals, Frontend Handbook.",
              "markups": [
                {
                  "type": 3,
                  "start": 137,
                  "end": 150,
                  "href": "https://cssreference.io/",
                  "title": "",
                  "rel": "",
                  "anchorType": 0
                },
                {
                  "type": 3,
                  "start": 152,
                  "end": 166,
                  "href": "https://htmlreference.io/",
                  "title": "",
                  "rel": "noopener",
                  "anchorType": 0
                },
                {
                  "type": 3,
                  "start": 168,
                  "end": 191,
                  "href": "https://github.com/leonardomso/33-js-concepts",
                  "title": "",
                  "rel": "noopener",
                  "anchorType": 0
                },
                {
                  "type": 3,
                  "start": 193,
                  "end": 210,
                  "href": "https://frontendmasters.com/books/front-end-handbook/2019/",
                  "title": "",
                  "rel": "noopener",
                  "anchorType": 0
                }
              ]
            },
            {
              "name": "2168",
              "type": 3,
              "text": "2. Get Started By Reading The Documentation",
              "markups": []
            },
            {
              "name": "3d49",
              "type": 1,
              "text": "Most developers are curious and want to jump straight to writing code and experimenting with it. That├ö├ç├ûs all good and fun but it├ö├ç├ûs not the most efficient way to go about mastering a framework or tools.",
              "markups": []
            },
            {
              "name": "a974",
              "type": 1,
              "text": "Reading the documentation is going to help you save time smashing your keyboard trying to figure out how a feature works. It will also spare you from re-implementing existing features that you didn├ö├ç├ût know about.",
              "markups": []
            },
            {
              "name": "041e",
              "type": 1,
              "text": "Make sure you read the whole documentation as it is your guide to understanding the ins and outs of the framework.",
              "markups": [
                {
                  "type": 1,
                  "start": 23,
                  "end": 28
                }
              ]
            },
            {
              "name": "108d",
              "type": 7,
              "text": "Most of your questions are answered in the docs. If they are not, then you get to contribute to the framework and help others, win-win.",
              "markups": []
            },
            {
              "name": "2d11",
              "type": 3,
              "text": "3. Understand The Build Process",
              "markups": []
            },
            {
              "name": "1932",
              "type": 1,
              "text": "Most frameworks provide you with out of the box build process through a CLI such as angular-cli or create-react-app.",
              "markups": []
            },
            {
              "name": "8b07",
              "type": 1,
              "text": "You should know what is happening behind the scenes in order to modify and tweak your build process as your application develops.",
              "markups": []
            },
            {
              "name": "78ad",
              "type": 1,
              "text": "Start with understanding the essential concepts such as transpiring, bundling, minifying and packaging. Afterward, you can move into the ├ö├ç├┐nice-to-have├ö├ç├û like linters, hot-reloaders, and git hooks.",
              "markups": []
            },
            {
              "name": "dac9",
              "type": 1,
              "text": "Once you feel confident in your understanding, bring the pieces together by choosing one of the popular bundlers (webpack/parcel) and start building your first application from scratch.",
              "markups": [
                {
                  "type": 3,
                  "start": 140,
                  "end": 185,
                  "href": "https://developerhandbook.com/webpack/webpack-4-from-absolute-scratch/",
                  "title": "",
                  "rel": "",
                  "anchorType": 0
                }
              ]
            },
            {
              "name": "a57f",
              "type": 3,
              "text": "4. Read The Style Guide",
              "markups": []
            },
            {
              "name": "dcf1",
              "type": 1,
              "text": "Antipatterns and pitfalls are more common than you think, you can learn from other people├ö├ç├ûs mistakes and avoid wasting yourself and the company lots of valuable time.",
              "markups": []
            },
            {
              "name": "6a8b",
              "type": 1,
              "text": "The style guide contains lots of helpful best practices that help you understand the framework even further and have a consistent coding style along with your teammates.",
              "markups": []
            },
            {
              "name": "56ad",
              "type": 1,
              "text": "You can also enforce these using linters such as vue-eslint-plugin.",
              "markups": [
                {
                  "type": 3,
                  "start": 49,
                  "end": 66,
                  "href": "https://eslint.vuejs.org/user-guide/#usage",
                  "title": "",
                  "rel": "noopener",
                  "anchorType": 0
                }
              ]
            },
            {
              "name": "3e6d",
              "type": 14,
              "text": "Style Guide - Vue.js\nThis is the official style guide for Vue-specific code. If you use Vue in a project, it's a great reference to avoid├ö├ç┬¬vuejs.org",
              "markups": [
                {
                  "type": 3,
                  "start": 0,
                  "end": 147,
                  "href": "https://vuejs.org/v2/style-guide/#Prop-definitions-essential",
                  "title": "https://vuejs.org/v2/style-guide/#Prop-definitions-essential",
                  "rel": "",
                  "anchorType": 0
                },
                {
                  "type": 1,
                  "start": 0,
                  "end": 20
                },
                {
                  "type": 2,
                  "start": 21,
                  "end": 138
                }
              ],
              "mixtapeMetadata": {
                "mediaResourceId": "d4afdef4e53e8bb242087dd4f8272835",
                "thumbnailImageId": "0*lV-3vkdZn0S7Z1lb",
                "href": "https://vuejs.org/v2/style-guide/#Prop-definitions-essential"
              }
            },
            {
              "name": "f850",
              "type": 3,
              "text": "5. Get Hold of The Devtools",
              "markups": []
            },
            {
              "name": "7747",
              "type": 1,
              "text": "Debugging is one of the most valuable tools you have in your toolbox. Developers often read more code than they write and therefore it├ö├ç├ûs very important to be able to debug code quickly.",
              "markups": []
            },
            {
              "name": "bfa3",
              "type": 1,
              "text": "Using the dev-tools browser extensions, you can view and change the components state and props, track custom events, observe route changes, locate your component in the DOM, and do much more.",
              "markups": []
            },
            {
              "name": "5e5c",
              "type": 1,
              "text": "Mastering the dev tools will massively increase your productivity over common debugging methods like console.log or debugger.",
              "markups": [
                {
                  "type": 10,
                  "start": 101,
                  "end": 112
                },
                {
                  "type": 10,
                  "start": 116,
                  "end": 124
                }
              ]
            },
            {
              "name": "9bf7",
              "type": 14,
              "text": "Debug React applications with the new React DevTools - LogRocket Blog\nDebugging is one of the most useful skills a developer can possess. It allows you to properly navigate and spot errors├ö├ç┬¬blog.logrocket.com",
              "markups": [
                {
                  "type": 3,
                  "start": 0,
                  "end": 207,
                  "href": "https://blog.logrocket.com/debug-react-applications-with-the-new-react-devtools/",
                  "title": "https://blog.logrocket.com/debug-react-applications-with-the-new-react-devtools/",
                  "rel": "",
                  "anchorType": 0
                },
                {
                  "type": 1,
                  "start": 0,
                  "end": 69
                },
                {
                  "type": 2,
                  "start": 70,
                  "end": 189
                }
              ],
              "mixtapeMetadata": {
                "mediaResourceId": "b94d635b5cd9d95c6ea99d5abe56592d",
                "thumbnailImageId": "0*uvRjmdpKrhqJrtzl",
                "href": "https://blog.logrocket.com/debug-react-applications-with-the-new-react-devtools/"
              }
            },
            {
              "name": "953a",
              "type": 3,
              "text": "6. Grasp Reactivity",
              "markups": []
            },
            {
              "name": "c682",
              "type": 1,
              "text": "React and Vue both heavily rely on reactivity systems. Grasping these mental models allow you to understand how the framework is built so you can optimize your usage.",
              "markups": []
            },
            {
              "name": "9dbf",
              "type": 1,
              "text": "In your journey, you will realize how frameworks listen to state changes and update your DOM automatically. You will also learn about virtual dom and untangle the confusion with shadow dom.",
              "markups": []
            },
            {
              "name": "dac6",
              "type": 1,
              "text": "Moreover, you will get a deep introduction to declarative programming and how it compares imperative programming which will yield in a great shift in how your write code.",
              "markups": []
            },
            {
              "name": "b018",
              "type": 1,
              "text": "There is an amazing course on Frontend Masters by Evan You where he explains the reactivity system of Vuejs from the ground up.",
              "markups": [
                {
                  "type": 3,
                  "start": 20,
                  "end": 58,
                  "href": "https://frontendmasters.com/courses/advanced-vue/introducing-reactivity/",
                  "title": "",
                  "rel": "",
                  "anchorType": 0
                }
              ]
            },
            {
              "name": "5ce5",
              "type": 3,
              "text": "7. Find Out Different Component Patterns",
              "markups": []
            },
            {
              "name": "589c",
              "type": 1,
              "text": "Components are the fundamental units of modern frontend systems. The ability to design and architect several components can have a huge impact on the long term on your project├ö├ç├ûs maintainability.",
              "markups": []
            },
            {
              "name": "5f69",
              "type": 1,
              "text": "Equipping yourself with different methodologies and patterns will allow you to scale up your application and introduce new features at ease.",
              "markups": []
            },
            {
              "name": "702e",
              "type": 1,
              "text": "Check out these two articles Advance Vuejs Component Patterns and Advanced React Component Patterns for an in-depth explanation.",
              "markups": [
                {
                  "type": 3,
                  "start": 29,
                  "end": 61,
                  "href": "https://medium.com/javascript-in-plain-english/advanced-vuejs-component-patterns-3ab1e1f0ed07",
                  "title": "",
                  "rel": "",
                  "anchorType": 0
                },
                {
                  "type": 3,
                  "start": 66,
                  "end": 99,
                  "href": "https://kentcdodds.com/blog/advanced-react-component-patterns/",
                  "title": "",
                  "rel": "",
                  "anchorType": 0
                }
              ]
            },
            {
              "name": "e3b4",
              "type": 3,
              "text": "8. Write Composable Code",
              "markups": []
            },
            {
              "name": "c91d",
              "type": 6,
              "text": "Code composition is one of the attributes of well-designed software systems.",
              "markups": []
            },
            {
              "name": "7ffd",
              "type": 1,
              "text": "Leveraging code composition you will be able to reuse existing code, and come up with bigger composable pieces and hence avoid having too many components.",
              "markups": [
                {
                  "type": 1,
                  "start": 134,
                  "end": 138
                },
                {
                  "type": 2,
                  "start": 134,
                  "end": 138
                }
              ]
            },
            {
              "name": "7801",
              "type": 1,
              "text": "Almost all communities have established a set of patterns to compose your code such as react-hooks or in the vue world, the vue-composition API, and mixins.",
              "markups": [
                {
                  "type": 3,
                  "start": 42,
                  "end": 57,
                  "href": "https://www.telerik.com/blogs/react-hooks-and-component-composition",
                  "title": "",
                  "rel": "",
                  "anchorType": 0
                }
              ]
            },
            {
              "name": "6b0c",
              "type": 1,
              "text": "Look in your codebase and search for potential use-cases to experiment with these patterns and see if it improves your codebase.",
              "markups": []
            },
            {
              "name": "7cf4",
              "type": 3,
              "text": "9. Optimize Components Communication",
              "markups": []
            },
            {
              "name": "a1b9",
              "type": 1,
              "text": "In modern frontend systems, a component-based strategy is often followed, where every component has a specific behavior and responsibility.",
              "markups": []
            },
            {
              "name": "41d4",
              "type": 1,
              "text": "This often results in having tens or even hundreds of components, and of course, component communication becomes an interesting topic that needs to be tackled elegantly.",
              "markups": []
            },
            {
              "name": "008d",
              "type": 1,
              "text": "Several strategies emerged to help in providing solutions such as the flux pattern, event emissions or callbacks and props.",
              "markups": []
            },
            {
              "name": "10dc",
              "type": 14,
              "text": "Do Your Vue Components Communicate Correctly?\nSeven patterns, pick the right onemedium.com",
              "markups": [
                {
                  "type": 3,
                  "start": 0,
                  "end": 90,
                  "href": "https://medium.com/better-programming/do-your-vue-components-communicate-correctly-9239c30cc495",
                  "title": "https://medium.com/better-programming/do-your-vue-components-communicate-correctly-9239c30cc495",
                  "rel": "",
                  "anchorType": 0
                },
                {
                  "type": 1,
                  "start": 0,
                  "end": 45
                },
                {
                  "type": 2,
                  "start": 46,
                  "end": 80
                }
              ],
              "mixtapeMetadata": {
                "mediaResourceId": "a3c315f9f77a17391165733e0a599a88",
                "thumbnailImageId": "0*HHQL8mw2WfRq8Ldd",
                "href": "https://medium.com/better-programming/do-your-vue-components-communicate-correctly-9239c30cc495"
              }
            },
            {
              "name": "f97d",
              "type": 3,
              "text": "10. Cover Your Code With Automated Tests",
              "markups": []
            },
            {
              "name": "f3ff",
              "type": 1,
              "text": "This is hands down one of the most challenging tasks in front-end development yet most teams, unfortunately, are not doing enough automated testing on the frontend.",
              "markups": []
            },
            {
              "name": "5bab",
              "type": 1,
              "text": "Having different browsers and screen sizes to supports, lots of the heavy lifting being moved to the fronted makes it crucial to have automated tests in place if you want to maintain your product quality.",
              "markups": []
            },
            {
              "name": "be2f",
              "type": 1,
              "text": "Explore unit tests, snapshot tests, and end to end tests.",
              "markups": []
            },
            {
              "name": "44f1",
              "type": 14,
              "text": "Pragmatic Front-End Testing Strategies (1)\nPart 1: Necessity of Pragmatic Front-End Testing Strategiesmedium.com",
              "markups": [
                {
                  "type": 3,
                  "start": 0,
                  "end": 112,
                  "href": "https://medium.com/@toastui/pragmatic-front-end-testing-strategies-1-4a969ab09453",
                  "title": "https://medium.com/@toastui/pragmatic-front-end-testing-strategies-1-4a969ab09453",
                  "rel": "",
                  "anchorType": 0
                },
                {
                  "type": 1,
                  "start": 0,
                  "end": 42
                },
                {
                  "type": 2,
                  "start": 43,
                  "end": 102
                }
              ],
              "mixtapeMetadata": {
                "mediaResourceId": "f6838b5c9cb18eaf2bfa6cf3d84193e4",
                "thumbnailImageId": "1*jYHepkLchSmgG1LJMMTzYA.png",
                "href": "https://medium.com/@toastui/pragmatic-front-end-testing-strategies-1-4a969ab09453"
              }
            },
            {
              "name": "778b",
              "type": 3,
              "text": "10. Get Out Of Your Comfort Zone",
              "markups": []
            },
            {
              "name": "c1f9",
              "type": 1,
              "text": "At some point, with enough practice, you will feel confident enough in your framework of choice. This is the point where you should jump ships and explore another framework.",
              "markups": []
            },
            {
              "name": "369a",
              "type": 1,
              "text": "Getting out of your comfort zone will allow you to have an objective view on the differences between frameworks and understand that the whole framework wars are pointless.",
              "markups": []
            },
            {
              "name": "33be",
              "type": 1,
              "text": "You will also be able to transfer some concepts over and your ability to jump from one framework to another will skyrocket. So go ahead and learn new frameworks be it React, Angular, Vue or Stencil there are tons of them I├ö├ç├ûm sure you will find one you like.",
              "markups": []
            },
            {
              "name": "152c",
              "type": 3,
              "text": "11. Go Beyond",
              "markups": []
            },
            {
              "name": "2387",
              "type": 1,
              "text": "I believe that most likely if you reached this point you will be acing most of the tasks that get into your way. Nevertheless, the world of frontend has no ends.",
              "markups": []
            },
            {
              "name": "aa13",
              "type": 1,
              "text": "Go and explore topics such as server-side rendering, Jamstack, accessibility, mobile applications, desktop application, service workers, algorithms, functional programming.",
              "markups": []
            },
            {
              "name": "4921",
              "type": 3,
              "text": "12. Remember To Have Fun",
              "markups": []
            },
            {
              "name": "af7c",
              "type": 1,
              "text": "Programming can be fun and enjoyable, if you are always writing code you might lose this feeling so I recommend that you start a side project with no financial benefits, no learning purpose, just for fun.",
              "markups": []
            },
            {
              "name": "506e",
              "type": 1,
              "text": "Building something you want to use, experiment with technology, do the things you always wanted to do and never had time for.",
              "markups": []
            },
            {
              "name": "d9bd",
              "type": 1,
              "text": "Thanks for reading, I hope that you use this quarantine as an opportunity to grow and learn more. Be Safe and enjoy your stay at home.",
              "markups": []
            },
            {
              "name": "7a70",
              "type": 13,
              "text": "A note from JavaScript In Plain English:",
              "markups": [
                {
                  "type": 1,
                  "start": 0,
                  "end": 40
                }
              ]
            },
            {
              "name": "b0f2",
              "type": 1,
              "text": "We are always interested in helping to promote quality content. If you have an article that you would like to submit to JavaScript In Plain English, send us an email at submissions@javascriptinplainenglish.com with your Medium username and we will get you added as a writer.",
              "markups": [
                {
                  "type": 3,
                  "start": 169,
                  "end": 209,
                  "href": "mailto:submissions@javascriptinplainenglish.com",
                  "title": "",
                  "rel": "",
                  "anchorType": 0
                }
              ]
            }
          ],
          "sections": [
            {
              "name": "0e6a",
              "startIndex": 0
            },
            {
              "name": "e0e4",
              "startIndex": 64
            }
          ]
        },
        "postDisplay": {
          "coverless": true
        }
      },
      "virtuals": {
        "statusForCollection": "APPROVED",
        "allowNotes": true,
        "previewImage": {
          "imageId": "0*G4aXwIEIiN6KfbSm",
          "filter": "",
          "backgroundSize": "",
          "originalWidth": 4584,
          "originalHeight": 3456,
          "strategy": "resample",
          "height": 0,
          "width": 0
        },
        "wordCount": 1408,
        "imageCount": 1,
        "readingTime": 5.513207547169811,
        "subtitle": "Quarantine Might Be Your Golden Chance",
        "publishedInCount": 1,
        "usersBySocialRecommends": [],
        "noIndex": false,
        "recommends": 186,
        "isBookmarked": false,
        "tags": [
          {
            "slug": "front-end-development",
            "name": "Front End Development",
            "postCount": 17140,
            "metadata": {
              "postCount": 17140,
              "coverImage": {
                "id": "0*vLnDia-gqHG6ny8z",
                "originalWidth": 5184,
                "originalHeight": 3456,
                "isFeatured": true,
                "unsplashPhotoId": "L8KQIPCODV8"
              }
            },
            "type": "Tag"
          },
          {
            "slug": "javascript",
            "name": "JavaScript",
            "postCount": 135430,
            "metadata": {
              "postCount": 135430,
              "coverImage": {
                "id": "1*B6GgsuFx7SyLuHcKDmnNfw.png",
                "originalWidth": 614,
                "originalHeight": 460,
                "isFeatured": true
              }
            },
            "type": "Tag"
          },
          {
            "slug": "programming",
            "name": "Programming",
            "postCount": 150561,
            "metadata": {
              "postCount": 150561,
              "coverImage": {
                "id": "0*ccx9xWjo-5pKk79i",
                "originalWidth": 1000,
                "originalHeight": 666,
                "isFeatured": true
              }
            },
            "type": "Tag"
          },
          {
            "slug": "react",
            "name": "React",
            "postCount": 40694,
            "metadata": {
              "postCount": 40694,
              "coverImage": {
                "id": "0*lIYGOdkZoD9RVFH4",
                "originalWidth": 5183,
                "originalHeight": 3670,
                "isFeatured": true,
                "unsplashPhotoId": "dQLgop4tnsc"
              }
            },
            "type": "Tag"
          },
          {
            "slug": "vue",
            "name": "Vue",
            "postCount": 2707,
            "metadata": {
              "postCount": 2707,
              "coverImage": {
                "id": "1*oGppz_lFrCY2sW6j_DYtgQ.png",
                "originalWidth": 2212,
                "originalHeight": 1136,
                "isFeatured": true
              }
            },
            "type": "Tag"
          }
        ],
        "socialRecommendsCount": 0,
        "responsesCreatedCount": 2,
        "links": {
          "entries": [
            {
              "url": "mailto:submissions@javascriptinplainenglish.com",
              "alts": [],
              "httpStatus": 0
            },
            {
              "url": "https://unsplash.com?utm_source=medium&utm_medium=referral",
              "alts": [],
              "httpStatus": 200
            },
            {
              "url": "https://vuejs.org/v2/style-guide/#Prop-definitions-essential",
              "alts": [],
              "httpStatus": 200
            },
            {
              "url": "https://htmlreference.io/",
              "alts": [],
              "httpStatus": 200
            },
            {
              "url": "https://cssreference.io/",
              "alts": [],
              "httpStatus": 200
            },
            {
              "url": "https://developerhandbook.com/webpack/webpack-4-from-absolute-scratch/",
              "alts": [],
              "httpStatus": 200
            },
            {
              "url": "https://eslint.vuejs.org/user-guide/#usage",
              "alts": [],
              "httpStatus": 200
            },
            {
              "url": "https://unsplash.com/@opak?utm_source=medium&utm_medium=referral",
              "alts": [],
              "httpStatus": 200
            },
            {
              "url": "https://medium.com/@toastui/pragmatic-front-end-testing-strategies-1-4a969ab09453",
              "alts": [
                {
                  "type": 3,
                  "url": "medium://p/4a969ab09453"
                },
                {
                  "type": 2,
                  "url": "medium://p/4a969ab09453"
                }
              ],
              "httpStatus": 200
            },
            {
              "url": "https://frontendmasters.com/courses/advanced-vue/introducing-reactivity/",
              "alts": [],
              "httpStatus": 200
            },
            {
              "url": "https://css-tricks.com/want-senior-developer/",
              "alts": [],
              "httpStatus": 200
            },
            {
              "url": "https://blog.logrocket.com/debug-react-applications-with-the-new-react-devtools/",
              "alts": [],
              "httpStatus": 200
            },
            {
              "url": "https://github.com/leonardomso/33-js-concepts",
              "alts": [],
              "httpStatus": 200
            },
            {
              "url": "https://kentcdodds.com/blog/advanced-react-component-patterns/",
              "alts": [],
              "httpStatus": 200
            },
            {
              "url": "https://medium.com/javascript-in-plain-english/advanced-vuejs-component-patterns-3ab1e1f0ed07",
              "alts": [
                {
                  "type": 3,
                  "url": "medium://p/3ab1e1f0ed07"
                },
                {
                  "type": 2,
                  "url": "medium://p/3ab1e1f0ed07"
                }
              ],
              "httpStatus": 200
            },
            {
              "url": "https://frontendmasters.com/books/front-end-handbook/2019/",
              "alts": [],
              "httpStatus": 200
            },
            {
              "url": "https://medium.com/better-programming/do-your-vue-components-communicate-correctly-9239c30cc495",
              "alts": [
                {
                  "type": 3,
                  "url": "medium://p/9239c30cc495"
                },
                {
                  "type": 2,
                  "url": "medium://p/9239c30cc495"
                }
              ],
              "httpStatus": 200
            },
            {
              "url": "https://www.telerik.com/blogs/react-hooks-and-component-composition",
              "alts": [
                {
                  "type": 1,
                  "url": "https://cdn.ampproject.org/c/s/www.telerik.com/amp/react-hooks-and-component-composition/WEx1ZE1sRUVUWkE5S0dNbEhBNXJyUkU3T1Q4PQ2"
                }
              ],
              "httpStatus": 200
            }
          ],
          "version": "0.3",
          "generatedAt": 1586162628559
        },
        "isLockedPreviewOnly": false,
        "metaDescription": "",
        "totalClapCount": 710,
        "sectionCount": 2,
        "readingList": 0,
        "topics": [
          {
            "topicId": "63c6f1f93ee",
            "slug": "javascript",
            "createdAt": 1493945704961,
            "deletedAt": 0,
            "image": {
              "id": "1*5UyyDJ1ESD11yQNd1UVAaQ@2x.jpeg",
              "originalWidth": 5472,
              "originalHeight": 3648
            },
            "name": "Javascript",
            "description": "An ode to code.",
            "relatedTopics": [],
            "visibility": 1,
            "relatedTags": [],
            "relatedTopicIds": [],
            "seoTitle": "Javascript News and Articles├ö├ç├¿├ö├ç├Â├ö├ç├¿Medium",
            "type": "Topic"
          }
        ]
      },
      "coverless": true,
      "slug": "a-practical-guide-to-become-a-senior-frontend-developer",
      "translationSourcePostId": "",
      "translationSourceCreatorId": "",
      "isApprovedTranslation": false,
      "inResponseToPostId": "",
      "inResponseToRemovedAt": 0,
      "isTitleSynthesized": false,
      "allowResponses": true,
      "importedUrl": "",
      "importedPublishedAt": 0,
      "visibility": 2,
      "uniqueSlug": "a-practical-guide-to-become-a-senior-frontend-developer-553ec50e2933",
      "previewContent": {
        "bodyModel": {
          "paragraphs": [
            {
              "name": "previewImage",
              "type": 4,
              "text": "",
              "layout": 10,
              "metadata": {
                "id": "0*G4aXwIEIiN6KfbSm",
                "originalWidth": 4584,
                "originalHeight": 3456,
                "isFeatured": true,
                "unsplashPhotoId": "P6mdg0z5tHc"
              }
            },
            {
              "name": "1430",
              "type": 3,
              "text": "A Practical Guide To Become a Senior Frontend Developer",
              "markups": [],
              "alignment": 1
            },
            {
              "name": "06a5",
              "type": 13,
              "text": "Quarantine Might Be Your Golden Chance",
              "markups": [],
              "alignment": 1
            }
          ],
          "sections": [
            {
              "startIndex": 0
            }
          ]
        },
        "isFullContent": false,
        "subtitle": "Quarantine Might Be Your Golden Chance"
      },
      "license": 0,
      "inResponseToMediaResourceId": "",
      "canonicalUrl": "https://medium.com/javascript-in-plain-english/a-practical-guide-to-become-a-senior-frontend-developer-553ec50e2933",
      "approvedHomeCollectionId": "4b3a1ed4f11c",
      "newsletterId": "",
      "webCanonicalUrl": "https://medium.com/javascript-in-plain-english/a-practical-guide-to-become-a-senior-frontend-developer-553ec50e2933",
      "mediumUrl": "https://medium.com/javascript-in-plain-english/a-practical-guide-to-become-a-senior-frontend-developer-553ec50e2933",
      "migrationId": "",
      "notifyFollowers": true,
      "notifyTwitter": false,
      "notifyFacebook": false,
      "responseHiddenOnParentPostAt": 0,
      "isSeries": false,
      "isSubscriptionLocked": true,
      "seriesLastAppendedAt": 0,
      "audioVersionDurationSec": 0,
      "sequenceId": "",
      "isEligibleForRevenue": true,
      "isBlockedFromHightower": false,
      "deletedAt": 0,
      "lockedPostSource": 1,
      "hightowerMinimumGuaranteeStartsAt": 0,
      "hightowerMinimumGuaranteeEndsAt": 0,
      "featureLockRequestAcceptedAt": 0,
      "mongerRequestType": 1,
      "layerCake": 3,
      "socialTitle": "",
      "socialDek": "",
      "editorialPreviewTitle": "",
      "editorialPreviewDek": "",
      "curationEligibleAt": 1586100290569,
      "primaryTopic": {
        "topicId": "63c6f1f93ee",
        "slug": "javascript",
        "createdAt": 1493945704961,
        "deletedAt": 0,
        "image": {
          "id": "1*5UyyDJ1ESD11yQNd1UVAaQ@2x.jpeg",
          "originalWidth": 5472,
          "originalHeight": 3648
        },
        "name": "Javascript",
        "description": "An ode to code.",
        "relatedTopics": [],
        "visibility": 1,
        "relatedTags": [],
        "relatedTopicIds": [],
        "seoTitle": "Javascript News and Articles├ö├ç├¿├ö├ç├Â├ö├ç├¿Medium",
        "type": "Topic"
      },
      "primaryTopicId": "63c6f1f93ee",
      "isProxyPost": false,
      "proxyPostFaviconUrl": "",
      "proxyPostProviderName": "",
      "proxyPostType": 0,
      "isSuspended": false,
      "isLimitedState": false,
      "seoTitle": "",
      "previewContent2": {
        "bodyModel": {
          "paragraphs": [
            {
              "name": "1430",
              "type": 3,
              "text": "A Practical Guide To Become a Senior Frontend Developer",
              "markups": []
            },
            {
              "name": "06a5",
              "type": 13,
              "text": "Quarantine Might Be Your Golden Chance",
              "markups": []
            },
            {
              "name": "62a6",
              "type": 1,
              "text": "There are several different definitions for the title ├ö├ç├┐Senior├ö├ç├û and it changes from one company to another. Yet, it├ö├ç├ûs agreed upon that there are are a lot of both hard and soft skills required.",
              "markups": []
            },
            {
              "name": "45ce",
              "type": 1,
              "text": "Chris Coyier wrote an article about character traits and behaviors that a senior frontend developer should├ö├ç┬¬",
              "markups": [
                {
                  "type": 3,
                  "start": 0,
                  "end": 30,
                  "href": "https://css-tricks.com/want-senior-developer/",
                  "title": "",
                  "rel": "",
                  "anchorType": 0
                }
              ]
            }
          ],
          "sections": [
            {
              "startIndex": 0
            }
          ]
        },
        "isFullContent": false,
        "subtitle": "Quarantine Might Be Your Golden Chance"
      },
      "cardType": 0,
      "isDistributionAlertDismissed": false,
      "isShortform": false,
      "shortformType": 0,
      "responsesLocked": false,
      "isLockedResponse": false,
      "type": "Post"
    },
    "mentionedUsers": [],
    "collaborators": [],
    "hideMeter": false,
    "collectionUserRelations": [],
    "mode": null,
    "references": {
      "User": {
        "2c4e5126ccb9": {
          "userId": "2c4e5126ccb9",
          "name": "Seifeldin Mahjoub",
          "username": "seif.sayed",
          "createdAt": 1442617579996,
          "imageId": "1*fH9uZQsXMWbV_wleMdmUsg.jpeg",
          "backgroundImageId": "",
          "bio": "Senior Frontend Developer @ShareNowglobal ├ö├ç├│ Writes about Vuejs and the Web.",
          "twitterScreenName": "SeifSayed",
          "socialStats": {
            "userId": "2c4e5126ccb9",
            "usersFollowedCount": 72,
            "usersFollowedByCount": 237,
            "type": "SocialStats"
          },
          "social": {
            "userId": "lo_3fo7uVuLCeYw",
            "targetUserId": "2c4e5126ccb9",
            "type": "Social"
          },
          "allowNotes": 1,
          "mediumMemberAt": 1548200082625,
          "isWriterProgramEnrolled": true,
          "isSuspended": false,
          "isMembershipTrialEligible": true,
          "optOutOfIceland": false,
          "type": "User"
        }
      },
      "Collection": {
        "4b3a1ed4f11c": {
          "id": "4b3a1ed4f11c",
          "name": "JavaScript In Plain English",
          "slug": "javascript-in-plain-english",
          "tags": [
            "JAVASCRIPT",
            "PROGRAMMING",
            "REACT",
            "WEB DEVELOPMENT",
            "FRONT END DEVELOPMENT"
          ],
          "creatorId": "a7b125868703",
          "description": "New articles every day.",
          "shortDescription": "New articles every day.",
          "image": {
            "imageId": "1*RCjOavj0Ym7St2BYky-L9w@2x.png",
            "filter": "",
            "backgroundSize": "",
            "originalWidth": 2048,
            "originalHeight": 2048,
            "strategy": "resample",
            "height": 0,
            "width": 0
          },
          "metadata": {
            "followerCount": 30432,
            "activeAt": 1594105360718
          },
          "virtuals": {
            "permissions": {
              "canPublish": false,
              "canPublishAll": false,
              "canRepublish": false,
              "canRemove": false,
              "canManageAll": false,
              "canSubmit": false,
              "canEditPosts": false,
              "canAddWriters": false,
              "canViewStats": false,
              "canSendNewsletter": false,
              "canViewLockedPosts": false,
              "canViewCloaked": false,
              "canEditOwnPosts": false,
              "canBeAssignedAuthor": false,
              "canEnrollInHightower": false,
              "canLockPostsForMediumMembers": false,
              "canLockOwnPostsForMediumMembers": false,
              "canViewNewsletterV2Stats": false,
              "canCreateNewsletterV3": false
            },
            "isSubscribed": false,
            "isEnrolledInHightower": false,
            "isEligibleForHightower": false,
            "isSubscribedToCollectionEmails": false,
            "isMuted": false,
            "canToggleEmail": false
          },
          "logo": {
            "imageId": "1*2cQFm_zRxhF1PRnNHOSegw@2x.png",
            "filter": "",
            "backgroundSize": "",
            "originalWidth": 4096,
            "originalHeight": 2048,
            "strategy": "resample",
            "height": 0,
            "width": 0
          },
          "twitterUsername": "JS_PlainEnglish",
          "publicEmail": "hello@plainenglish.io",
          "collectionMastheadId": "3648d9008ed8",
          "sections": [
            {
              "type": 2,
              "collectionHeaderMetadata": {
                "backgroundImage": {},
                "logoImage": {
                  "id": "1*5UkzzqJ9XIHA9M3TOP_GQw@2x.png",
                  "originalWidth": 2048,
                  "originalHeight": 2048,
                  "alt": "JavaScript In Plain English"
                },
                "alignment": 1,
                "layout": 6
              }
            },
            {
              "type": 1,
              "postListMetadata": {
                "source": 3,
                "layout": 4,
                "number": 3,
                "postIds": [
                  "a9876724dee8",
                  "c0bd2cc9b3f8",
                  "15c2584f51b9"
                ],
                "sectionHeader": "Now trending"
              }
            },
            {
              "type": 3,
              "promoMetadata": {
                "sectionHeader": "",
                "promoId": "f2734d7cc445"
              }
            },
            {
              "type": 1,
              "postListMetadata": {
                "source": 1,
                "layout": 4,
                "number": 25,
                "postIds": [],
                "sectionHeader": "Latest articles"
              }
            },
            {
              "type": 1,
              "postListMetadata": {
                "source": 1,
                "layout": 4,
                "number": 25,
                "postIds": []
              }
            },
            {
              "type": 1,
              "postListMetadata": {
                "source": 3,
                "layout": 4,
                "number": 1,
                "postIds": [
                  "b0854ead7d14"
                ]
              }
            },
            {
              "type": 3,
              "promoMetadata": {
                "sectionHeader": "",
                "promoId": "a04ee8196e7b"
              }
            }
          ],
          "tintColor": "#FF0000FF",
          "lightText": false,
          "favicon": {
            "imageId": "",
            "filter": "",
            "backgroundSize": "",
            "originalWidth": 0,
            "originalHeight": 0,
            "strategy": "resample",
            "height": 0,
            "width": 0
          },
          "colorPalette": {
            "defaultBackgroundSpectrum": {
              "colorPoints": [
                {
                  "color": "#FF297AFF",
                  "point": 0
                },
                {
                  "color": "#FF2B73FF",
                  "point": 0.1
                },
                {
                  "color": "#FF2C6CFB",
                  "point": 0.2
                },
                {
                  "color": "#FF2C64E0",
                  "point": 0.3
                },
                {
                  "color": "#FF2B5BC5",
                  "point": 0.4
                },
                {
                  "color": "#FF2952AB",
                  "point": 0.5
                },
                {
                  "color": "#FF274992",
                  "point": 0.6
                },
                {
                  "color": "#FF233E79",
                  "point": 0.7
                },
                {
                  "color": "#FF1D3361",
                  "point": 0.8
                },
                {
                  "color": "#FF172749",
                  "point": 0.9
                },
                {
                  "color": "#FF0F1A31",
                  "point": 1
                }
              ],
              "backgroundColor": "#FFFFFFFF"
            },
            "tintBackgroundSpectrum": {
              "colorPoints": [
                {
                  "color": "#FF0000FF",
                  "point": 0
                },
                {
                  "color": "#FF004BF8",
                  "point": 0.1
                },
                {
                  "color": "#FF2A6AF9",
                  "point": 0.2
                },
                {
                  "color": "#FF4A82FD",
                  "point": 0.3
                },
                {
                  "color": "#FF6597FF",
                  "point": 0.4
                },
                {
                  "color": "#FF7FABFF",
                  "point": 0.5
                },
                {
                  "color": "#FF98BDFF",
                  "point": 0.6
                },
                {
                  "color": "#FFAFCFFF",
                  "point": 0.7
                },
                {
                  "color": "#FFC6E0FF",
                  "point": 0.8
                },
                {
                  "color": "#FFDCF0FF",
                  "point": 0.9
                },
                {
                  "color": "#FFF2FFFF",
                  "point": 1
                }
              ],
              "backgroundColor": "#FF0000FF"
            },
            "highlightSpectrum": {
              "colorPoints": [
                {
                  "color": "#FFE2F4FF",
                  "point": 0
                },
                {
                  "color": "#FFDCF2FF",
                  "point": 0.1
                },
                {
                  "color": "#FFD7F1FF",
                  "point": 0.2
                },
                {
                  "color": "#FFD1EFFF",
                  "point": 0.3
                },
                {
                  "color": "#FFCBEDFF",
                  "point": 0.4
                },
                {
                  "color": "#FFC4EBFF",
                  "point": 0.5
                },
                {
                  "color": "#FFBEEAFF",
                  "point": 0.6
                },
                {
                  "color": "#FFB7E8FF",
                  "point": 0.7
                },
                {
                  "color": "#FFB1E5FF",
                  "point": 0.8
                },
                {
                  "color": "#FFA9E3FF",
                  "point": 0.9
                },
                {
                  "color": "#FFA2E1FF",
                  "point": 1
                }
              ],
              "backgroundColor": "#FFFFFFFF"
            }
          },
          "navItems": [
            {
              "type": 2,
              "title": "Write For Us",
              "postId": "b0854ead7d14",
              "url": "https://medium.com/javascript-in-plain-english/https-medium-com-javascript-in-plain-english-join-our-team-b0854ead7d14",
              "source": "postId"
            },
            {
              "type": 2,
              "title": "Style Guide",
              "postId": "6e661edb6d06",
              "url": "https://medium.com/javascript-in-plain-english/how-to-write-articles-that-people-want-to-read-6e661edb6d06",
              "source": "postId"
            },
            {
              "type": 5,
              "title": "Archive",
              "url": "https://medium.com/javascript-in-plain-english/archive"
            }
          ],
          "colorBehavior": 1,
          "instantArticlesState": 0,
          "acceleratedMobilePagesState": 0,
          "collectionFeatures": [
            27,
            25
          ],
          "ampLogo": {
            "imageId": "",
            "filter": "",
            "backgroundSize": "",
            "originalWidth": 0,
            "originalHeight": 0,
            "strategy": "resample",
            "height": 0,
            "width": 0
          },
          "header": {
            "backgroundImage": {},
            "logoImage": {
              "id": "1*5UkzzqJ9XIHA9M3TOP_GQw@2x.png",
              "originalWidth": 2048,
              "originalHeight": 2048,
              "alt": "JavaScript In Plain English"
            },
            "alignment": 1,
            "layout": 6
          },
          "subscriberCount": 30432,
          "tagline": "New articles every day.",
          "instagramUsername": "inplainenglish",
          "isOptedIntoAurora": false,
          "newsletterV3": {
            "newsletterV3Id": "9af1374ad186",
            "type": 1,
            "name": "Sunil @ In Plain English",
            "description": "A weekly round up of the best content from In Plain English, handpicked by our Founder @sunilsandhu",
            "collectionId": "4b3a1ed4f11c",
            "newsletterSlug": "sunil-in-plain-english",
            "isSubscribed": false,
            "showPromo": false
          },
          "isCurationAllowedByDefault": false,
          "type": "Collection"
        }
      },
      "Social": {
        "2c4e5126ccb9": {
          "userId": "lo_3fo7uVuLCeYw",
          "targetUserId": "2c4e5126ccb9",
          "type": "Social"
        }
      },
      "SocialStats": {
        "2c4e5126ccb9": {
          "userId": "2c4e5126ccb9",
          "usersFollowedCount": 72,
          "usersFollowedByCount": 237,
          "type": "SocialStats"
        }
      }
    }
  },
  "v": 3,
  "b": "41543-dbbbf90"
}